{
	"disk_merged": {
		"title": "Disk Merged Operations ({{PI}}) on {{HOST}}",
		"vertical": "Merged operations/s",
		"type": "io",
		"legend": {
			"read": {
				"name": "Read",
				"color": "0000ff"
			},
			"write": {
				"name": "Write",
				"color": "00b000"
			}
		},
		"legend_format": "%5.1lf%s"
	},
	"disk_octets": {
		"title": "Disk Traffic ({{PI}}) on {{HOST}}",
		"vertical": "Bytes per second",
		"type": "io",
		"legend": {
			"read": {
				"name": "Read",
				"color": "0000ff"
			},
			"write": {
				"name": "Write",
				"color": "00b000"
			}
		},
		"legend_format": "%5.1lf%s"
	},
	"disk_ops": {
		"title": "Disk Operations ({{PI}}) on {{HOST}}",
		"vertical": "Ops per second",
		"type": "io",
		"legend": {
			"read": {
				"name": "Read",
				"color": "0000ff"
			},
			"write": {
				"name": "Write",
				"color": "00b000"
			}
		},
		"legend_format": "%5.1lf%s"
	},
	"disk_time": {
		"title": "Disk time per operation ({{PI}}) on {{HOST}}",
		"vertical": "Avg. Time/Op",
		"type": "io",
		"legend": {
			"read": {
				"name": "Read",
				"color": "0000ff"
			},
			"write": {
				"name": "Write",
				"color": "00b000"
			}
		},
		"legend_format": "%5.1lf%ss",
		"scale": 0.001
	},
	"pending_operations": {
		"title": "Disk Pending Operations ({{PI}}) on {{HOST}}",
		"vertical": "Operations",
		"legend": {
			"value": {
				"name": "Operations",
				"color": "0000f0"
			}
		},
		"legend_format": "%5.1lf%s"
	},
	"disk_io_time": {
		"title": "Disk time spent doing I/Os ({{PI}}) on {{HOST}}",
		"vertical": "I/O time (s)",
		"legend": {
			"io_time": {
				"name": "I/O Time",
				"color": "0000ff"
			},
			"weighted_io_time": {
				"name": "Weighted I/O Time",
				"color": "f0a000"
			}
		},
		"legend_format": "%5.1lf%ss",
		"scale": 0.001
	}
}
